tikka/__init__.py
tikka/__main__.py
tikka/adapters/__init__.py
tikka/adapters/network/__init__.py
tikka/adapters/network/network.py
tikka/adapters/network/datapod/__init__.py
tikka/adapters/network/datapod/connection.py
tikka/adapters/network/datapod/datapod.py
tikka/adapters/network/datapod/profiles.py
tikka/adapters/network/indexer/__init__.py
tikka/adapters/network/indexer/accounts.py
tikka/adapters/network/indexer/connection.py
tikka/adapters/network/indexer/identities.py
tikka/adapters/network/indexer/indexer.py
tikka/adapters/network/indexer/transfers.py
tikka/adapters/network/node/__init__.py
tikka/adapters/network/node/accounts.py
tikka/adapters/network/node/authorities.py
tikka/adapters/network/node/connection.py
tikka/adapters/network/node/currency.py
tikka/adapters/network/node/identities.py
tikka/adapters/network/node/node.py
tikka/adapters/network/node/smiths.py
tikka/adapters/network/node/substrate_client.py
tikka/adapters/network/node/technical_committee.py
tikka/adapters/network/node/transfers.py
tikka/adapters/repository/__init__.py
tikka/adapters/repository/accounts.py
tikka/adapters/repository/authorities.py
tikka/adapters/repository/categories.py
tikka/adapters/repository/config.py
tikka/adapters/repository/currencies.py
tikka/adapters/repository/currency.py
tikka/adapters/repository/datapods.py
tikka/adapters/repository/file_db_client.py
tikka/adapters/repository/file_wallets.py
tikka/adapters/repository/identities.py
tikka/adapters/repository/indexers.py
tikka/adapters/repository/nodes.py
tikka/adapters/repository/passwords.py
tikka/adapters/repository/preferences.py
tikka/adapters/repository/profiles.py
tikka/adapters/repository/repository.py
tikka/adapters/repository/smiths.py
tikka/adapters/repository/technical_committee_members.py
tikka/adapters/repository/technical_committee_proposals.py
tikka/adapters/repository/transfers.py
tikka/adapters/repository/wallets.py
tikka/adapters/repository/assets/config.json
tikka-0.19.0.dist-info/licenses/LICENSE
tikka-0.19.0.dist-info/METADATA
tikka-0.19.0.dist-info/WHEEL
tikka-0.19.0.dist-info/entry_points.txt
tikka-0.19.0.dist-info/top_level.txt
tikka-0.19.0.dist-info/RECORD
