Metadata-Version: 2.4
Name: tikka
Version: 0.19.0
Summary: Tikka is a fast and light Python/Tk client to manage your Ğ1 accounts
Author-email: Vincent Texier <vit@free.fr>
Requires-Python: >=3.9
License-File: LICENSE
Requires-Dist: mnemonic>=0.19
Requires-Dist: yoyo-migrations>=9.0.0
Requires-Dist: pyqt5<5.15.11,>=5.15.2
Requires-Dist: pyqt5-qt<5.15.11,>=5.15.2
Requires-Dist: pyqt5-qt5<5.15.11,>=5.15.2
Requires-Dist: pyyaml>=6.0
Requires-Dist: python-sql>=1.4.0
Requires-Dist: qrcode>=7.4.2
Requires-Dist: opencv-contrib-python>=4.8.0.74
Requires-Dist: eth-typing>=3.2
Requires-Dist: eth-utils<2.3
Requires-Dist: gql>=3.5.0
Requires-Dist: requests-toolbelt>=1.0.0
Requires-Dist: dateutils>=0.6.12
Requires-Dist: pyaes>=1.6.1
Requires-Dist: pyqtwebengine>=5.15.7
Requires-Dist: scalecodec>=1.2.12
Requires-Dist: pynacl>=1.6.1
Requires-Dist: eth-keys>=0.7.0
Requires-Dist: py-sr25519-bindings>=0.2.2
Requires-Dist: py-bip39-bindings>=0.3.0
Requires-Dist: xxhash>=3.6.0
Requires-Dist: websocket-client>=1.9.0
Requires-Dist: libnacl>=2.1.0
Requires-Dist: pycryptodome>=3.23.0
Requires-Dist: py-ed25519-zebra-bindings>=1.3.0
Dynamic: license-file
